odoo/addons/mass_mailing_event_registration_exclude/README.rst
odoo/addons/mass_mailing_event_registration_exclude/__init__.py
odoo/addons/mass_mailing_event_registration_exclude/__manifest__.py
odoo/addons/mass_mailing_event_registration_exclude/data/event_state_data.xml
odoo/addons/mass_mailing_event_registration_exclude/i18n/am.po
odoo/addons/mass_mailing_event_registration_exclude/i18n/ar.po
odoo/addons/mass_mailing_event_registration_exclude/i18n/bg.po
odoo/addons/mass_mailing_event_registration_exclude/i18n/bs.po
odoo/addons/mass_mailing_event_registration_exclude/i18n/ca.po
odoo/addons/mass_mailing_event_registration_exclude/i18n/cs.po
odoo/addons/mass_mailing_event_registration_exclude/i18n/da.po
odoo/addons/mass_mailing_event_registration_exclude/i18n/de.po
odoo/addons/mass_mailing_event_registration_exclude/i18n/el_GR.po
odoo/addons/mass_mailing_event_registration_exclude/i18n/en_GB.po
odoo/addons/mass_mailing_event_registration_exclude/i18n/es.po
odoo/addons/mass_mailing_event_registration_exclude/i18n/es_AR.po
odoo/addons/mass_mailing_event_registration_exclude/i18n/es_CL.po
odoo/addons/mass_mailing_event_registration_exclude/i18n/es_CO.po
odoo/addons/mass_mailing_event_registration_exclude/i18n/es_CR.po
odoo/addons/mass_mailing_event_registration_exclude/i18n/es_DO.po
odoo/addons/mass_mailing_event_registration_exclude/i18n/es_EC.po
odoo/addons/mass_mailing_event_registration_exclude/i18n/es_ES.po
odoo/addons/mass_mailing_event_registration_exclude/i18n/es_MX.po
odoo/addons/mass_mailing_event_registration_exclude/i18n/es_PE.po
odoo/addons/mass_mailing_event_registration_exclude/i18n/es_PY.po
odoo/addons/mass_mailing_event_registration_exclude/i18n/es_VE.po
odoo/addons/mass_mailing_event_registration_exclude/i18n/et.po
odoo/addons/mass_mailing_event_registration_exclude/i18n/eu.po
odoo/addons/mass_mailing_event_registration_exclude/i18n/fa.po
odoo/addons/mass_mailing_event_registration_exclude/i18n/fi.po
odoo_addon_mass_mailing_event_registration_exclude-18.0.1.0.0.2.dist-info/METADATA
odoo_addon_mass_mailing_event_registration_exclude-18.0.1.0.0.2.dist-info/WHEEL
odoo_addon_mass_mailing_event_registration_exclude-18.0.1.0.0.2.dist-info/top_level.txt
odoo_addon_mass_mailing_event_registration_exclude-18.0.1.0.0.2.dist-info/RECORD
